pymetadataeditor/__init__.py
pymetadataeditor/interface.py
pymetadataeditor/llm_helpers.py
pymetadataeditor/requester.py
pymetadataeditor/templates.py
pymetadataeditor/utils.py
pymetadataeditor-0.3.2.dist-info/LICENSE
pymetadataeditor-0.3.2.dist-info/METADATA
pymetadataeditor-0.3.2.dist-info/WHEEL
pymetadataeditor-0.3.2.dist-info/RECORD
