Metadata-Version: 2.1
Name: pymetadataeditor
Version: 0.3.2
Summary: Metadata Editor client for python
License: MIT
Author: Gordon Blackadder
Author-email: gblackadder@worldbank.org
Requires-Python: >=3.11,<4.0
Classifier: License :: OSI Approved :: MIT License
Classifier: Programming Language :: Python :: 3
Classifier: Programming Language :: Python :: 3.11
Classifier: Programming Language :: Python :: 3.12
Requires-Dist: markitdown (>=0.0.1a3,<0.0.2)
Requires-Dist: metadataschemas (>=0.1.3,<0.2.0)
Requires-Dist: openai (>=2.8.0,<3.0.0)
Requires-Dist: pandas (>=2.2.2,<3.0.0)
Requires-Dist: pydantic (>=2.7.4,<3.0.0)
Requires-Dist: requests (>=2.32.3,<3.0.0)
Requires-Dist: tiktoken (>=0.8.0,<0.9.0)
Requires-Dist: urllib3 (>=2.2.2,<3.0.0)
